[
    {
        "name":"CoeHarMod_2 更新日志",
        "civilopediaText":[
            // {"text":"1.新增电力系统。"},//TODO
            {"text":"\nv0.1.5-适合本体4.14.16"},
            {"text":"1.植树员不涨价且只能用金钱购买。"},
            {"text":"2.强化部分改良和奇观。"},

            {"text":"\nv0.1.4-适合本体4.14.16"},
            {"text":"1.尝试修复植树员人肉阻挡敌方近战的错误，不保证修好。"},
            {"text":"2.重做美国。"},

            {"text":"\nv0.1.3-适合本体4.14.16"},
            {"text":"1.调整自主。"},
            {"text":"2.专精建筑涨价幅度下调33%。"},
            {"text":"3.重做巴比伦。"},
            {"text":"4.删除水电站。"},

            {"text":"\nv0.1.2-适合本体4.14.16"},
            {"text":"1.新增明朝，重做印度。"},
            {"text":"2.调整自主。"},
            {"text":"3.取消丘陵城基座产能。"},
            {"text":"4.移民前两回合+2移动力。"},

            {"text":"\nv0.1.1-适合本体4.14.14"},
            {"text":"1.新增元朝，调整奥斯曼。"},
            {"text":"2.修复自主工人不加速的错误。"},
            {"text":"3.工船调整为与工人一样而非一次性。"},

            {"text":"\nv0.1.0"},
            {"text":"1.新增军队规模机制。"},
            {"text":"2.修复骑兵攻城没有惩罚的错误。"},
            {"text":"3.调整民族史诗的效果。"},
            {"text":"4.调整中后期政策。"},

            {"text":"\nv0.0.6"},
            {"text":"1.修复堡垒不提供防御的错误。"},
            {"text":"2.堡垒不得与市中心相邻，且防御力随科技增长。"},
            {"text":"3.微调商业右一，道路维护费减免改为修路时间减半。"},
            {"text":"4.抗骑兵单位增强。"},
            {"text":"5.允许种树。"},
            {"text":"6.调整锯木厂和贸易站。"},

            {"text":"\nv0.0.5"},
            {"text":"1.修复抗骑兵无晋升的错误。"},
            {"text":"2.抗骑兵取消负面效果，降低基础力。"},
            {"text":"3.调整雄鹰战士和波斯长生军。"},
            {"text":"4.调整蒙古和骑兵"},
            {"text":"5.取消虔信和理性的矛盾"},

            {"text":"\nv0.0.4"},
            {"text":"微调部分建筑和政策效果。"},

            {"text":"\nv0.0.3"},
            {"text":"1.抗骑兵单位对战普通近战单位（勇士Warrior）-50%战斗力。"},
            {"text":"2.取消单位补给机制。"},

            {"text":"\nv0.0.2"},
            {"text":"修复人口没能限制专精方向数量的错误。"},

            {"text":"\nv0.0.1"},
            {"text":"1.添加专精方向。"},
            {"text":"2.强化军事建筑/娱乐建筑/农田/矿井。"}
        ]
    }
]
